cnceye/__init__.py
cnceye/arc.py
cnceye/shape.py
cnceye-0.5.1.dist-info/LICENSE
cnceye-0.5.1.dist-info/METADATA
cnceye-0.5.1.dist-info/WHEEL
cnceye-0.5.1.dist-info/RECORD
