Metadata-Version: 2.1
Name: cnceye
Version: 0.5.1
Summary: CMM python library
Home-page: https://github.com/OpenCMM/cnceye
License: MIT
Keywords: cnc,cmm,milling,gcode
Author: yuichiroaoki
Author-email: 45054071+yuichiroaoki@users.noreply.github.com
Requires-Python: >=3.11,<3.13
Classifier: License :: OSI Approved :: MIT License
Classifier: Programming Language :: Python :: 3
Classifier: Programming Language :: Python :: 3.11
Requires-Dist: numpy (>=1.26.2,<2.0.0)
Requires-Dist: scipy (>=1.11.4,<2.0.0)
Requires-Dist: trimesh (>=4.0.5,<5.0.0)
Project-URL: Repository, https://github.com/OpenCMM/cnceye
